Workbook

Sheet RawData
A1: Product | B1: Units | C1: Price | D1: Cost
A2: Widget A | B2: 1000 | C2: 50 | D2: 20
A3: Widget B | B3: 800 | C3: 75 | D3: 30
A4: Widget C | B4: 1200 | C4: 40 | D4: 15
A5: Widget D | B5: 500 | C5: 120 | D5: 50
A6: Widget E | B6: 2000 | C6: 25 | D6: 10
B8: =SUM(B2:B6) | C8: =AVERAGE(C2:C6) | D8: =AVERAGE(D2:D6)

Sheet Assumptions
A1: Parameter | B1: Value
A2: GrowthRate | B2: 0.05
A3: TaxRate | B3: 0.21
A4: DiscountRate | B4: 0.08
A5: COGS_pct | B5: 0.4
A6: OpEx_pct | B6: 0.25
A7: DepreciationM | B7: 500
A8: InterestM | B8: 200
A9: OtherIncome | B9: 1000

Sheet Revenue
A1: Product | B1: Base Revenue | C1: Growth Adj | D1: Total Revenue
A2: =RawData!A2 | B2: =RawData!B2*RawData!C2 | C2: =B2*(1+Assumptions!B2) | D2: =B2+C2
A3: =RawData!A3 | B3: =RawData!B3*RawData!C3 | C3: =B3*(1+Assumptions!B2) | D3: =B3+C3
A4: =RawData!A4 | B4: =RawData!B4*RawData!C4 | C4: =B4*(1+Assumptions!B2) | D4: =B4+C4
A5: =RawData!A5 | B5: =RawData!B5*RawData!C5 | C5: =B5*(1+Assumptions!B2) | D5: =B5+C5
A6: =RawData!A6 | B6: =RawData!B6*RawData!C6 | C6: =B6*(1+Assumptions!B2) | D6: =B6+C6
B8: =SUM(B2:B6) | C8: =SUM(C2:C6) | D8: =SUM(D2:D6)
D10: Total
D11: =D8
A13: Ext Budget Ref | B13: ='[Budget_2026.xlsx]Forecast'!B5

Sheet COGS
A1: Product | B1: Units | C1: Unit Cost | D1: Total COGS
A2: =RawData!A2 | B2: =RawData!B2 | C2: =RawData!D2 | D2: =B2*C2
A3: =RawData!A3 | B3: =RawData!B3 | C3: =RawData!D3 | D3: =B3*C3
A4: =RawData!A4 | B4: =RawData!B4 | C4: =RawData!D4 | D4: =B4*C4
A5: =RawData!A5 | B5: =RawData!B5 | C5: =RawData!D5 | D5: =B5*C5
A6: =RawData!A6 | B6: =RawData!B6 | C6: =RawData!D6 | D6: =B6*C6
D8: =SUM(D2:D6)
B10: COGS % Check | C10: =D8/Revenue!D8 | D10: =Assumptions!B4
A13: Ext Cost Ref | B13: ='[Suppliers.xlsx]Costs'!C10

Sheet OpEx
A1: Category | B1: Amount
A2: Salaries | B2: =Revenue!D8*0.15
A3: Marketing | B3: =Revenue!D8*Assumptions!B5*0.4
A4: R&D | B4: =Revenue!D8*0.05
A5: Admin | B5: =Revenue!D8*0.03
A6: Facilities | B6: =Assumptions!B6
B8: =SUM(B2:B6)
A10: Depreciation | B10: =Assumptions!B6
A11: Total w/ Dep | B11: =B8+B10
A13: Ext Headcount | B13: ='[HR_Model.xlsx]Headcount'!D15

Sheet EBITDA
A1: Line Item | B1: Amount
A2: Revenue | B2: =Revenue!D8
A3: COGS | B3: =COGS!D8
A4: Gross Profit | B4: =B2-B3
A5: Gross Margin | B5: =B4/B2
A6: OpEx | B6: =OpEx!B8
A7: EBITDA | B7: =B4-B6
A8: EBITDA Margin | B8: =B7/B2
A10: Interest | B10: =Assumptions!B7
A11: EBIT | B11: =B7-B10
A13: Ext Benchmark | B13: ='[Industry_Benchmarks.xlsx]EBITDA'!C7

Sheet Tax
A1: Line Item | B1: Amount
A2: EBIT | B2: =EBITDA!B11
A3: Tax Rate | B3: =Assumptions!B3
A4: Tax Provision | B4: =B2*B3
A5: DTA Adjustment | B5: =B4*0.05
A6: Net Tax | B6: =B4-B5
A7: Effective Rate | B7: =B6/B2
A9: Ext Tax Guidance | B9: ='[Tax_Model.xlsx]Rates'!B12

Sheet NetIncome
A1: Line Item | B1: Amount
A2: EBIT | B2: =EBITDA!B11
A3: Tax | B3: =Tax!B6
A4: Other Income | B4: =Assumptions!B8
A5: Net Income | B5: =B2-B3+B4
A6: Net Margin | B6: =B5/Revenue!D8
A7: EPS (1M shares) | B7: =B5/1000000
A8: Retained Earnings | B8: =B5*0.6
A9: Dividends | B9: =B5*0.4

Sheet CashFlow
A1: Line Item | B1: Amount
A2: Net Income | B2: =NetIncome!B5
A3: Add: Depreciation | B3: =Assumptions!B6
A4: Change in WC | B4: =(COGS!D8+OpEx!B8)*(-0.05)
A5: Operating CF | B5: =B2+B3+B4
A6: CapEx | B6: =EBITDA!B7*0.08
A7: Free Cash Flow | B7: =B5-B6
A8: FCF Yield | B8: =B7/Revenue!D8
A9: Discounted FCF | B9: =B7/(1+Assumptions!B4)
A11: Ext Capex Plan | B11: ='[Capex_Schedule.xlsx]Plan'!E20

Sheet Summary
A1: KPI Dashboard
A3: Metric | B3: Value | C3: vs Prior Year
A4: Total Revenue | B4: =Revenue!D8 | C4: ='[Prior_Year.xlsx]Summary'!B4
A5: Gross Profit | B5: =EBITDA!B4 | C5: ='[Prior_Year.xlsx]Summary'!B5
A6: EBITDA | B6: =EBITDA!B7 | C6: ='[Prior_Year.xlsx]Summary'!B6
A7: Net Income | B7: =NetIncome!B5 | C7: ='[Prior_Year.xlsx]Summary'!B7
A8: Free Cash Flow | B8: =CashFlow!B7 | C8: ='[Prior_Year.xlsx]Summary'!B8
A9: COGS | B9: =COGS!D8 | C9: ='[Prior_Year.xlsx]Summary'!B9
A10: Total OpEx | B10: =OpEx!B8 | C10: ='[Prior_Year.xlsx]Summary'!B10
A11: Tax Provision | B11: =Tax!B4 | C11: ='[Prior_Year.xlsx]Summary'!B11
A12: Gross Margin % | B12: =EBITDA!B5 | C12: ='[Prior_Year.xlsx]Summary'!B12
A13: Net Margin % | B13: =NetIncome!B6 | C13: ='[Prior_Year.xlsx]Summary'!B13
A15: Assumptions Cross-check | B15: =Assumptions!B2 | C15: =Assumptions!B3 | D15: =Assumptions!B4
